Handtrackingmodulee/__init__.py
Handtrackingmodulee/handtrackingmodule.py
HandTrackingModulevarun-1.0.0.0.dist-info/LICENSE
HandTrackingModulevarun-1.0.0.0.dist-info/METADATA
HandTrackingModulevarun-1.0.0.0.dist-info/WHEEL
HandTrackingModulevarun-1.0.0.0.dist-info/top_level.txt
HandTrackingModulevarun-1.0.0.0.dist-info/RECORD
