Metadata-Version: 2.1
Name: HandTrackingModulevarun
Version: 1.0.0.0
Summary: handtrackingmodule
Home-page: UNKNOWN
Author: Varun Gupta
Author-email: Varun.gupta.py@gmail.com
License: UNKNOWN
Keywords: Hand Tracking Module,hand tracking module,Varun Gupta,varun gupta,opencv python,cv2,opencv
Platform: UNKNOWN
Classifier: Development Status :: 1 - Planning
Classifier: Intended Audience :: Developers
Classifier: Programming Language :: Python :: 3
Classifier: Operating System :: Unix
Classifier: Operating System :: MacOS :: MacOS X
Classifier: Operating System :: Microsoft :: Windows
License-File: LICENSE
Requires-Dist: opencv-python
